djjwt/__init__.py
djjwt/middleware.py
djjwt/urls.py
djjwt/views.py
dj_jwt-0.0.2.dist-info/LICENSE
dj_jwt-0.0.2.dist-info/METADATA
dj_jwt-0.0.2.dist-info/WHEEL
dj_jwt-0.0.2.dist-info/top_level.txt
dj_jwt-0.0.2.dist-info/RECORD
