Metadata-Version: 2.1
Name: dj-jwt
Version: 0.0.2
Summary: Library to give vanilla Django jwt auth.
Home-page: https://github.com/buddylindsey/dj-jwt
Author: Buddy Lindsey
Author-email: buddy@buddylindsey.com
Maintainer: Buddy Lindsey
License: UNKNOWN
Project-URL: Documentation, https://github.com/buddylindsey/dj-jwt
Project-URL: Source, https://github.com/buddylindsey/dj-jwt
Platform: UNKNOWN
Classifier: Development Status :: 4 - Beta
Classifier: Intended Audience :: Developers
Classifier: Natural Language :: English
Classifier: License :: OSI Approved :: MIT License
Classifier: Programming Language :: Python
Classifier: Programming Language :: Python :: 3
Classifier: Programming Language :: Python :: 3.7
Classifier: Programming Language :: Python :: 3.8
Classifier: Programming Language :: Python :: 3.9
Classifier: Framework :: Django
Classifier: Framework :: Django :: 3.0
Requires-Python: >=3.7
Requires-Dist: djangorestframework-simplejwt (<4.8,>=4.7)
